{"nodes": [{"id": "src_prediction_factors_py", "label": "factors.py", "file_type": "code", "source_file": "src/prediction/factors.py", "source_location": "L1"}, {"id": "factors_factoradjustment", "label": "FactorAdjustment", "file_type": "code", "source_file": "src/prediction/factors.py", "source_location": "L36"}, {"id": "factors_factoradjuster", "label": "FactorAdjuster", "file_type": "code", "source_file": "src/prediction/factors.py", "source_location": "L43"}, {"id": "factors_factoradjuster_init", "label": ".__init__()", "file_type": "code", "source_file": "src/prediction/factors.py", "source_location": "L50"}, {"id": "factors_factoradjuster_get_factors_for_game", "label": ".get_factors_for_game()", "file_type": "code", "source_file": "src/prediction/factors.py", "source_location": "L59"}, {"id": "factors_factoradjuster_add_factor", "label": ".add_factor()", "file_type": "code", "source_file": "src/prediction/factors.py", "source_location": "L72"}, {"id": "factors_factoradjuster_remove_factor", "label": ".remove_factor()", "file_type": "code", "source_file": "src/prediction/factors.py", "source_location": "L115"}, {"id": "factors_factoradjuster_list_factors", "label": ".list_factors()", "file_type": "code", "source_file": "src/prediction/factors.py", "source_location": "L127"}, {"id": "factors_factoradjuster_bulk_import_factors", "label": ".bulk_import_factors()", "file_type": "code", "source_file": "src/prediction/factors.py", "source_location": "L149"}, {"id": "factors_factoradjuster_calculate_adjustment", "label": ".calculate_adjustment()", "file_type": "code", "source_file": "src/prediction/factors.py", "source_location": "L188"}, {"id": "factors_apply_game_factors", "label": "apply_game_factors()", "file_type": "code", "source_file": "src/prediction/factors.py", "source_location": "L207"}, {"id": "factors_get_factor_type_descriptions", "label": "get_factor_type_descriptions()", "file_type": "code", "source_file": "src/prediction/factors.py", "source_location": "L271"}, {"id": "factors_rationale_1", "label": "Game factors module for prediction adjustments (future use).", "file_type": "rationale", "source_file": "src/prediction/factors.py", "source_location": "L1"}, {"id": "factors_rationale_37", "label": "Represents an adjustment to be applied to a prediction.", "file_type": "rationale", "source_file": "src/prediction/factors.py", "source_location": "L37"}, {"id": "factors_rationale_44", "label": "Handles game factor adjustments for predictions.      Provides the framework for", "file_type": "rationale", "source_file": "src/prediction/factors.py", "source_location": "L44"}, {"id": "factors_rationale_51", "label": "Initialize the factor adjuster.          Args:             db: Database instance", "file_type": "rationale", "source_file": "src/prediction/factors.py", "source_location": "L51"}, {"id": "factors_rationale_60", "label": "Get all factors associated with a game.          Args:             game_id: Game", "file_type": "rationale", "source_file": "src/prediction/factors.py", "source_location": "L60"}, {"id": "factors_rationale_80", "label": "Add a factor to a game.          Args:             game_id: Game ID", "file_type": "rationale", "source_file": "src/prediction/factors.py", "source_location": "L80"}, {"id": "factors_rationale_116", "label": "Remove a factor by ID.          Args:             factor_id: Factor ID to remove", "file_type": "rationale", "source_file": "src/prediction/factors.py", "source_location": "L116"}, {"id": "factors_rationale_128", "label": "List all factors for a game in a display-friendly format.          Args:", "file_type": "rationale", "source_file": "src/prediction/factors.py", "source_location": "L128"}, {"id": "factors_rationale_150", "label": "Import factors from a CSV file.          CSV format:         game_id,team_id,fac", "file_type": "rationale", "source_file": "src/prediction/factors.py", "source_location": "L150"}, {"id": "factors_rationale_189", "label": "Calculate the win probability adjustment for a single factor.          Args:", "file_type": "rationale", "source_file": "src/prediction/factors.py", "source_location": "L189"}, {"id": "factors_rationale_211", "label": "Apply game factors to adjust a base prediction.      Calculates per-factor proba", "file_type": "rationale", "source_file": "src/prediction/factors.py", "source_location": "L211"}, {"id": "factors_rationale_272", "label": "Get descriptions for all factor types.      Returns:         Dictionary mapping", "file_type": "rationale", "source_file": "src/prediction/factors.py", "source_location": "L272"}], "edges": [{"source": "src_prediction_factors_py", "target": "csv", "relation": "imports", "confidence": "EXTRACTED", "source_file": "src/prediction/factors.py", "source_location": "L3", "weight": 1.0}, {"source": "src_prediction_factors_py", "target": "logging", "relation": "imports", "confidence": "EXTRACTED", "source_file": "src/prediction/factors.py", "source_location": "L4", "weight": 1.0}, {"source": "src_prediction_factors_py", "target": "dataclasses", "relation": "imports_from", "confidence": "EXTRACTED", "source_file": "src/prediction/factors.py", "source_location": "L5", "weight": 1.0}, {"source": "src_prediction_factors_py", "target": "typing", "relation": "imports_from", "confidence": "EXTRACTED", "source_file": "src/prediction/factors.py", "source_location": "L6", "weight": 1.0}, {"source": "src_prediction_factors_py", "target": "src_database_db_py", "relation": "imports_from", "confidence": "EXTRACTED", "source_file": "src/prediction/factors.py", "source_location": "L8", "weight": 1.0}, {"source": "src_prediction_factors_py", "target": "src_database_models_py", "relation": "imports_from", "confidence": "EXTRACTED", "source_file": "src/prediction/factors.py", "source_location": "L9", "weight": 1.0}, {"source": "src_prediction_factors_py", "target": "factors_factoradjustment", "relation": "contains", "confidence": "EXTRACTED", "source_file": "src/prediction/factors.py", "source_location": "L36", "weight": 1.0}, {"source": "src_prediction_factors_py", "target": "factors_factoradjuster", "relation": "contains", "confidence": "EXTRACTED", "source_file": "src/prediction/factors.py", "source_location": "L43", "weight": 1.0}, {"source": "factors_factoradjuster", "target": "factors_factoradjuster_init", "relation": "method", "confidence": "EXTRACTED", "source_file": "src/prediction/factors.py", "source_location": "L50", "weight": 1.0}, {"source": "factors_factoradjuster", "target": "factors_factoradjuster_get_factors_for_game", "relation": "method", "confidence": "EXTRACTED", "source_file": "src/prediction/factors.py", "source_location": "L59", "weight": 1.0}, {"source": "factors_factoradjuster", "target": "factors_factoradjuster_add_factor", "relation": "method", "confidence": "EXTRACTED", "source_file": "src/prediction/factors.py", "source_location": "L72", "weight": 1.0}, {"source": "factors_factoradjuster", "target": "factors_factoradjuster_remove_factor", "relation": "method", "confidence": "EXTRACTED", "source_file": "src/prediction/factors.py", "source_location": "L115", "weight": 1.0}, {"source": "factors_factoradjuster", "target": "factors_factoradjuster_list_factors", "relation": "method", "confidence": "EXTRACTED", "source_file": "src/prediction/factors.py", "source_location": "L127", "weight": 1.0}, {"source": "factors_factoradjuster", "target": "factors_factoradjuster_bulk_import_factors", "relation": "method", "confidence": "EXTRACTED", "source_file": "src/prediction/factors.py", "source_location": "L149", "weight": 1.0}, {"source": "factors_factoradjuster", "target": "factors_factoradjuster_calculate_adjustment", "relation": "method", "confidence": "EXTRACTED", "source_file": "src/prediction/factors.py", "source_location": "L188", "weight": 1.0}, {"source": "src_prediction_factors_py", "target": "factors_apply_game_factors", "relation": "contains", "confidence": "EXTRACTED", "source_file": "src/prediction/factors.py", "source_location": "L207", "weight": 1.0}, {"source": "src_prediction_factors_py", "target": "factors_get_factor_type_descriptions", "relation": "contains", "confidence": "EXTRACTED", "source_file": "src/prediction/factors.py", "source_location": "L271", "weight": 1.0}, {"source": "factors_factoradjuster_list_factors", "target": "factors_factoradjuster_get_factors_for_game", "relation": "calls", "confidence": "EXTRACTED", "source_file": "src/prediction/factors.py", "source_location": "L137", "weight": 1.0}, {"source": "factors_factoradjuster_bulk_import_factors", "target": "factors_factoradjuster_add_factor", "relation": "calls", "confidence": "EXTRACTED", "source_file": "src/prediction/factors.py", "source_location": "L170", "weight": 1.0}, {"source": "factors_apply_game_factors", "target": "factors_factoradjuster", "relation": "calls", "confidence": "EXTRACTED", "source_file": "src/prediction/factors.py", "source_location": "L231", "weight": 1.0}, {"source": "factors_apply_game_factors", "target": "factors_factoradjuster_calculate_adjustment", "relation": "calls", "confidence": "EXTRACTED", "source_file": "src/prediction/factors.py", "source_location": "L234", "weight": 1.0}, {"source": "factors_rationale_1", "target": "src_prediction_factors_py", "relation": "rationale_for", "confidence": "EXTRACTED", "source_file": "src/prediction/factors.py", "source_location": "L1", "weight": 1.0}, {"source": "factors_rationale_37", "target": "factors_factoradjustment", "relation": "rationale_for", "confidence": "EXTRACTED", "source_file": "src/prediction/factors.py", "source_location": "L37", "weight": 1.0}, {"source": "factors_rationale_44", "target": "factors_factoradjuster", "relation": "rationale_for", "confidence": "EXTRACTED", "source_file": "src/prediction/factors.py", "source_location": "L44", "weight": 1.0}, {"source": "factors_rationale_51", "target": "factors_factoradjuster_init", "relation": "rationale_for", "confidence": "EXTRACTED", "source_file": "src/prediction/factors.py", "source_location": "L51", "weight": 1.0}, {"source": "factors_rationale_60", "target": "factors_factoradjuster_get_factors_for_game", "relation": "rationale_for", "confidence": "EXTRACTED", "source_file": "src/prediction/factors.py", "source_location": "L60", "weight": 1.0}, {"source": "factors_rationale_80", "target": "factors_factoradjuster_add_factor", "relation": "rationale_for", "confidence": "EXTRACTED", "source_file": "src/prediction/factors.py", "source_location": "L80", "weight": 1.0}, {"source": "factors_rationale_116", "target": "factors_factoradjuster_remove_factor", "relation": "rationale_for", "confidence": "EXTRACTED", "source_file": "src/prediction/factors.py", "source_location": "L116", "weight": 1.0}, {"source": "factors_rationale_128", "target": "factors_factoradjuster_list_factors", "relation": "rationale_for", "confidence": "EXTRACTED", "source_file": "src/prediction/factors.py", "source_location": "L128", "weight": 1.0}, {"source": "factors_rationale_150", "target": "factors_factoradjuster_bulk_import_factors", "relation": "rationale_for", "confidence": "EXTRACTED", "source_file": "src/prediction/factors.py", "source_location": "L150", "weight": 1.0}, {"source": "factors_rationale_189", "target": "factors_factoradjuster_calculate_adjustment", "relation": "rationale_for", "confidence": "EXTRACTED", "source_file": "src/prediction/factors.py", "source_location": "L189", "weight": 1.0}, {"source": "factors_rationale_211", "target": "factors_apply_game_factors", "relation": "rationale_for", "confidence": "EXTRACTED", "source_file": "src/prediction/factors.py", "source_location": "L211", "weight": 1.0}, {"source": "factors_rationale_272", "target": "factors_get_factor_type_descriptions", "relation": "rationale_for", "confidence": "EXTRACTED", "source_file": "src/prediction/factors.py", "source_location": "L272", "weight": 1.0}], "raw_calls": [{"caller_nid": "factors_factoradjuster_get_factors_for_game", "callee": "get_game_factors", "source_file": "src/prediction/factors.py", "source_location": "L69"}, {"caller_nid": "factors_factoradjuster_get_factors_for_game", "callee": "from_row", "source_file": "src/prediction/factors.py", "source_location": "L70"}, {"caller_nid": "factors_factoradjuster_add_factor", "callee": "FactorType", "source_file": "src/prediction/factors.py", "source_location": "L95"}, {"caller_nid": "factors_factoradjuster_add_factor", "callee": "ValueError", "source_file": "src/prediction/factors.py", "source_location": "L98"}, {"caller_nid": "factors_factoradjuster_add_factor", "callee": "ValueError", "source_file": "src/prediction/factors.py", "source_location": "L105"}, {"caller_nid": "factors_factoradjuster_add_factor", "callee": "insert_game_factor", "source_file": "src/prediction/factors.py", "source_location": "L107"}, {"caller_nid": "factors_factoradjuster_remove_factor", "callee": "remove_game_factor", "source_file": "src/prediction/factors.py", "source_location": "L125"}, {"caller_nid": "factors_factoradjuster_bulk_import_factors", "callee": "open", "source_file": "src/prediction/factors.py", "source_location": "L166"}, {"caller_nid": "factors_factoradjuster_bulk_import_factors", "callee": "DictReader", "source_file": "src/prediction/factors.py", "source_location": "L167"}, {"caller_nid": "factors_factoradjuster_bulk_import_factors", "callee": "int", "source_file": "src/prediction/factors.py", "source_location": "L171"}, {"caller_nid": "factors_factoradjuster_bulk_import_factors", "callee": "int", "source_file": "src/prediction/factors.py", "source_location": "L172"}, {"caller_nid": "factors_factoradjuster_bulk_import_factors", "callee": "get", "source_file": "src/prediction/factors.py", "source_location": "L174"}, {"caller_nid": "factors_factoradjuster_bulk_import_factors", "callee": "int", "source_file": "src/prediction/factors.py", "source_location": "L175"}, {"caller_nid": "factors_factoradjuster_bulk_import_factors", "callee": "get", "source_file": "src/prediction/factors.py", "source_location": "L175"}, {"caller_nid": "factors_factoradjuster_bulk_import_factors", "callee": "error", "source_file": "src/prediction/factors.py", "source_location": "L179"}, {"caller_nid": "factors_factoradjuster_bulk_import_factors", "callee": "error", "source_file": "src/prediction/factors.py", "source_location": "L183"}, {"caller_nid": "factors_factoradjuster_calculate_adjustment", "callee": "get", "source_file": "src/prediction/factors.py", "source_location": "L199"}, {"caller_nid": "factors_apply_game_factors", "callee": "max", "source_file": "src/prediction/factors.py", "source_location": "L247"}, {"caller_nid": "factors_apply_game_factors", "callee": "min", "source_file": "src/prediction/factors.py", "source_location": "L247"}, {"caller_nid": "factors_apply_game_factors", "callee": "max", "source_file": "src/prediction/factors.py", "source_location": "L248"}, {"caller_nid": "factors_apply_game_factors", "callee": "min", "source_file": "src/prediction/factors.py", "source_location": "L248"}, {"caller_nid": "factors_apply_game_factors", "callee": "Prediction", "source_file": "src/prediction/factors.py", "source_location": "L256"}, {"caller_nid": "factors_apply_game_factors", "callee": "copy", "source_file": "src/prediction/factors.py", "source_location": "L264"}]}